pandasai_bedrock/__init__.py
pandasai_bedrock/base.py
pandasai_bedrock/claude.py
pandasai_bedrock-0.1.5.dist-info/METADATA
pandasai_bedrock-0.1.5.dist-info/WHEEL
pandasai_bedrock-0.1.5.dist-info/RECORD
